laonlp_spellchecker/__init__.py
laonlp_spellchecker/lao_words_with_freq.txt
laonlp_spellchecker/spellchecker.py
laonlp_spellchecker-0.1.9.dist-info/METADATA
laonlp_spellchecker-0.1.9.dist-info/WHEEL
laonlp_spellchecker-0.1.9.dist-info/top_level.txt
laonlp_spellchecker-0.1.9.dist-info/RECORD
