Metadata-Version: 2.1
Name: laonlp-spellchecker
Version: 0.1.9
Summary: A Lao NLP library for spell-checking
Home-page: https://github.com/Monaliza14xx/laonlp_spellchecker
Author: Khonepaseuth SOUNAKHEN
Author-email: khonepaserth@fe-nuol.edu.la
Classifier: Programming Language :: Python :: 3
Classifier: License :: OSI Approved :: MIT License
Classifier: Operating System :: OS Independent
Requires-Python: >=3.6
Requires-Dist: symspellpy
